{
  "id": "x6qq-d7ac",
  "rowDisplayUnit": "car",
  "defaultAggregateColumn": ":count",
  "domain": "dataspace-demo.test-socrata.com",
  "ownerId": "",
  "updatedAt": "",
  "columns": [
    {
      "title": "Tow Date",
      "name": "tow_date",
      "physicalDatatype": "timestamp",
      "logicalDatatype": "time",
      "importance": 2
    },
    {
      "title": "Make",
      "name": "make",
      "physicalDatatype": "text",
      "logicalDatatype": "category",
      "importance": 2
    },
    {
      "title": "Style",
      "name": "style",
      "physicalDatatype": "text",
      "logicalDatatype": "category",
      "importance": 3
    },
    {
      "title": "Model",
      "name": "model",
      "physicalDatatype": "text",
      "logicalDatatype": "category",
      "importance": 2
    },
    {
      "title": "Color",
      "name": "color",
      "physicalDatatype": "text",
      "logicalDatatype": "category",
      "importance": 2
    },
    {
      "title": "Plate",
      "name": "plate",
      "physicalDatatype": "text",
      "logicalDatatype": "identifier",
      "importance": 1
    },
    {
      "title": "State",
      "name": "state",
      "physicalDatatype": "text",
      "logicalDatatype": "category",
      "importance": 1
    },
    {
      "title": "Towed to Address",
      "name": "towed_to_address",
      "physicalDatatype": "text",
      "logicalDatatype": "text",
      "importance": 3
    },
    {
      "title": "Tow Facility Phone",
      "name": "tow_facility_phone",
      "physicalDatatype": "text",
      "logicalDatatype": "text",
      "importance": 3
    },
    {
      "title": "Inventory Number",
      "name": "inventory_number",
      "physicalDatatype": "text",
      "logicalDatatype": "identifier",
      "importance": 3
    }
  ]
}
